pytransposer/__init__.py
pytransposer/common.py
pytransposer/config.py
pytransposer/transposer.py
pytransposer-1.3.2.dist-info/METADATA
pytransposer-1.3.2.dist-info/WHEEL
pytransposer-1.3.2.dist-info/licenses/LICENSE
pytransposer-1.3.2.dist-info/RECORD
