Metadata-Version: 2.1
Name: pytransposer
Version: 1.3.2
Summary: A python package for transposing chords from one key to another and changing between DO-RE-MI and A-B-C notations.
Project-URL: Homepage, https://github.com/bfrangi/pytransposer
Project-URL: Bug Tracker, https://github.com/bfrangi/pytransposer/issues
Author-email: bfrangi <bernat.frangi@gmail.com>
License-File: LICENSE
Classifier: License :: OSI Approved :: GNU General Public License v3 (GPLv3)
Classifier: Operating System :: OS Independent
Classifier: Programming Language :: Python :: 3
Requires-Python: >=3.8
